[
  {
    "type": "manametalmod:ManaMetalInjection",
    "items": [
      "manametalmod:Pineapple_crop",
      "manametalmod:Pineapple_crop",
      "manametalmod:Pineapple_crop",
      "manametalmod:Pineapple_crop",
      "manametalmod:Pineapple_crop",
      "manametalmod:Pineapple_crop",
      "manametalmod:Pineapple_crop",
      "manametalmod:Pineapple_crop",
      "manametalmod:Pineapple_crop"
    ],
    "output": "manametalmod:Pineapple_crop",
    "count": 10
  },
  {
    "type": "manametalmod:ManaCraftTable",
    "items": [
      "manametalmod:Pineapple_crop",
      "manametalmod:Pineapple_crop",
      "manametalmod:Pineapple_crop",
      "manametalmod:Pineapple_crop",
      "manametalmod:Pineapple_crop",
      "manametalmod:Pineapple_crop",
      "manametalmod:Pineapple_crop",
      "manametalmod:Pineapple_crop",
      "manametalmod:Pineapple_crop"
    ],
    "output": "manametalmod:Pineapple_crop",
    "count": 10
  },
  {
    "type": "manametalmod:MetalCraftTable",
    "items": [
      "manametalmod:Pineapple_crop",
      "manametalmod:Pineapple_crop",
      "manametalmod:Pineapple_crop",
      "manametalmod:Pineapple_crop",
      "manametalmod:Pineapple_crop",
      "manametalmod:Pineapple_crop",
      "manametalmod:Pineapple_crop",
      "manametalmod:Pineapple_crop",
      "manametalmod:Pineapple_crop"
    ],
    "output": "manametalmod:Pineapple_crop",
    "count": 10
  },
  {
    "type": "manametalmod:Baking",
    "items": [
      "manametalmod:Pineapple_crop",
      "manametalmod:Pineapple_crop"
    ],
    "output": "manametalmod:Pineapple_crop",
    "count": 1
  },
  {
    "type": "manametalmod:Juicer",
    "items": [
      "manametalmod:Pineapple_seed",
      "manametalmod:Pineapple_seed"
    ],
    "output": "manametalmod:ItemNewFatigueWaters",
    "count": 2
  },
  {
    "type": "manametalmod:Grinding",
    "items": [
      "manametalmod:Pineapple_crop",
      "manametalmod:Pineapple_crop"
    ],
    "output": "manametalmod:Pineapple_seed",
    "count": 2
  },
  {
    "type": "manametalmod:Fermentation",
    "items": [
      "manametalmod:Pineapple_seed",
      "manametalmod:Pineapple_seed"
    ],
    "output": "manametalmod:ItemComposters",
    "count": 2
  },
  {
    "type": "manametalmod:Bartender",
    "items": [
      "manametalmod:Pineapple_crop",
      "manametalmod:Pineapple_crop"
    ],
    "output": "manametalmod:ItemWineF",
    "count": 1
  }
]